pyFMQTT.py
fstkmqtt/TrafficApp.py
fstkmqtt/__init__.py
fstkmqtt/traffic_adstract.py
fstkmqtt-0.0.1a0.dist-info/METADATA
fstkmqtt-0.0.1a0.dist-info/WHEEL
fstkmqtt-0.0.1a0.dist-info/top_level.txt
fstkmqtt-0.0.1a0.dist-info/RECORD
