Metadata-Version: 2.1
Name: fstkmqtt
Version: 0.0.1a0
Summary: Full project name: Fullstack MQTT for engineering
Download-URL: https://sourceforge.net/projects/fstkmqtt
Author: Samson
Author-email: kaioffrayce@gmail.com
